botshop/__init__.py
botshop/conversation_engine.py
botshop/io_processor.py
botshop/model_evaluator.py
botshop/sample_and_rank.py
botshop/simple_bot.py
botshop/pytorch/__init__.py
botshop/pytorch/conversation_engine.py
botshop/pytorch/sample_and_rank.py
botshop/pytorch/utils.py
botshop-0.0.45.dist-info/LICENSE
botshop-0.0.45.dist-info/METADATA
botshop-0.0.45.dist-info/WHEEL
botshop-0.0.45.dist-info/top_level.txt
botshop-0.0.45.dist-info/RECORD
