Metadata-Version: 2.1
Name: botshop
Version: 0.0.45
Summary: Framework for chatbot model inference, optimized for neural conversation models.
Home-page: https://github.com/nuhame/botshop
Author: Freddy Snijder
Author-email: botshop@visionscapers.com
Classifier: Programming Language :: Python :: 3.7
Classifier: License :: OSI Approved :: Apache Software License
Classifier: Operating System :: OS Independent
Requires-Python: >=3.7
License-File: LICENSE
Requires-Dist: numpy
Requires-Dist: visionscaper-pybase
